Metadata-Version: 1.2
Name: windowsprefetch
Version: 4.0.3
Summary: A Python script to parse Windows Prefetch files
Home-page: https://github.com/PoorBillionaire/Windows-Prefetch-Parser
Author: Adam Witt
Author-email: accidentalassist@gmail.com
License: Apache Software License
Keywords: DFIR Prefetch Forensics Incident Response Microsoft Windows
Platform: UNKNOWN
Classifier: Development Status :: 5 - Production/Stable
Classifier: Intended Audience :: Information Technology
Classifier: Topic :: Security
Classifier: License :: OSI Approved :: Apache Software License
Requires-Python: >=3
